sudoku/__init__.py
sudoku/solver.py
sudoku/strategies.py
sudoku/sudoku.py
simple_sudoku_solver-1.0.0.dist-info/METADATA
simple_sudoku_solver-1.0.0.dist-info/WHEEL
simple_sudoku_solver-1.0.0.dist-info/top_level.txt
simple_sudoku_solver-1.0.0.dist-info/RECORD
