Metadata-Version: 2.1
Name: simple-sudoku-solver
Version: 1.0.0
Summary: Basic library to solve sudoku
Home-page: https://github.com/stuartmccord/sudoku
Author: Stuart McCord
Author-email: stuart.mccord@gmail.com
License: MIT
Platform: UNKNOWN
Classifier: License :: OSI Approved :: MIT License
Classifier: Programming Language :: Python :: 3
Classifier: Programming Language :: Python :: 3.7
